qolvoters/__init__.py
qolvoters/qolvoters.py
qolvoters-1.0.dist-info/LICENSE.txt
qolvoters-1.0.dist-info/METADATA
qolvoters-1.0.dist-info/WHEEL
qolvoters-1.0.dist-info/top_level.txt
qolvoters-1.0.dist-info/RECORD
