Metadata-Version: 2.1
Name: qolvoters
Version: 1.0
Summary: This library execute voter participation rate analysis for the Quality of Life Exporer variables
Home-page: https://github.com/ProvidenceAdu/qolvoters
Author: Providence Adu,Ph.D.
Author-email: <padu@charlotte.edu>
Keywords: urban institute,python,Mecklenburg County,quality of life explorer,voters,NPA
License-File: LICENSE.txt
Requires-Dist: pandas (>=1.0.0)
